CHANGES.rst
CONTRIBUTORS.rst
LICENSE.GPL
LICENSE.rst
MANIFEST.in
README.rst
TODO.rst
package.json
pip-selfcheck.json
setup.cfg
setup.py
collective/__init__.py
collective.permalink.egg-info/PKG-INFO
collective.permalink.egg-info/SOURCES.txt
collective.permalink.egg-info/dependency_links.txt
collective.permalink.egg-info/entry_points.txt
collective.permalink.egg-info/namespace_packages.txt
collective.permalink.egg-info/not-zip-safe
collective.permalink.egg-info/requires.txt
collective.permalink.egg-info/top_level.txt
collective/permalink/__init__.py
collective/permalink/adapters.py
collective/permalink/browser.py
collective/permalink/configure.zcml
collective/permalink/interfaces.py
collective/permalink/setuphandlers.py
collective/permalink/testing.py
collective/permalink/profiles/default/actions.xml
collective/permalink/profiles/default/browserlayer.xml
collective/permalink/profiles/default/controlpanel.xml
collective/permalink/profiles/default/metadata.xml
collective/permalink/profiles/default/registry.xml
collective/permalink/profiles/default/rolemap.xml
collective/permalink/profiles/uninstall/actions.xml
collective/permalink/profiles/uninstall/browserlayer.xml
collective/permalink/profiles/uninstall/controlpanel.xml
collective/permalink/profiles/uninstall/registry.xml
collective/permalink/profiles/uninstall/rolemap.xml
collective/permalink/static/clipboard.js
collective/permalink/static/clipboard.min.js
collective/permalink/static/script.js
collective/permalink/tests/__init__.py
collective/permalink/tests/test_setup.py
docs/screenshot_plone4.png
docs/sponsor_akbild.png
docs/sponsor_azienda.gif
docs/sponsor_redturtle.png
eggs/Products.CMFDiffTool-3.1.6-py2.7.egg/Products/CMFDiffTool/locales/pt_BR/LC_MESSAGES/collective.dexteritydiff.mo
eggs/Products.PlacelessTranslationService-2.0.7-py2.7.egg/Products/PlacelessTranslationService/locales/cs/LC_MESSAGES/PlacelessTranslationService.mo
eggs/Products.PlacelessTranslationService-2.0.7-py2.7.egg/Products/PlacelessTranslationService/locales/de/LC_MESSAGES/PlacelessTranslationService.mo
eggs/Products.PlacelessTranslationService-2.0.7-py2.7.egg/Products/PlacelessTranslationService/locales/el/LC_MESSAGES/PlacelessTranslationService.mo
