Metadata-Version: 2.1
Name: collective.permalink
Version: 1.0.4
Summary: Show a new link (permalink) in Plone contents. This will not change if you move the content itself.
Home-page: https://github.com/collective/collective.permalink
Author: RedTurtle Technology
Author-email: sviluppoplone@redturtle.it
License: GPL
Keywords: plone plonegov permalink
Platform: UNKNOWN
Classifier: Environment :: Web Environment
Classifier: Framework :: Plone
Classifier: Framework :: Plone :: 5.0
Classifier: Programming Language :: Python
Classifier: Programming Language :: Python :: 2.7
Classifier: Operating System :: OS Independent
Classifier: License :: OSI Approved :: GNU General Public License v2 (GPLv2)
Provides-Extra: test
